requestMr/__init__.py
requestMr/grpc/__init__.py
requestMr/grpc/client.py
requestMr/grpc/soa_invoke_pb2.py
requestMr/grpc/soa_invoke_pb2_grpc.py
requestMr-1.0.9.dist-info/METADATA
requestMr-1.0.9.dist-info/WHEEL
requestMr-1.0.9.dist-info/top_level.txt
requestMr-1.0.9.dist-info/RECORD
