Metadata-Version: 2.1
Name: requestMr
Version: 1.0.9
Summary: test framework
Home-page: UNKNOWN
Author: maoyongfan
Author-email: maoyongfan@163.com
License: MIT
Keywords: api test python language frameworks
Platform: UNKNOWN
Classifier: Development Status :: 3 - Alpha
Classifier: Intended Audience :: Developers
Classifier: Topic :: Software Development :: Build Tools
Classifier: License :: OSI Approved :: MIT License
Classifier: Programming Language :: Python :: 3
Classifier: Programming Language :: Python :: 3.7
Classifier: Operating System :: OS Independent
Requires-Python: >=3
Requires-Dist: grpcio (==1.33.1)
Requires-Dist: grpcio-tools (==1.33.1)
Requires-Dist: protobuf (==3.13.0)
